sal/__init__.py
sal/client/__init__.py
sal/client/main.py
sal/core/VERSION
sal/core/__init__.py
sal/core/exception.py
sal/core/path.py
sal/core/serialise.py
sal/core/time.py
sal/core/version.py
sal/core/object/__init__.py
sal/core/object/branch.py
sal/core/object/dataclass.py
sal/core/object/report.py
sal/core/tests/__init__.py
sal/core/tests/test_path.py
sal/dataclass/__init__.py
sal/dataclass/core/__init__.py
sal/dataclass/core/array.py
sal/dataclass/core/dictionary.py
sal/dataclass/core/scalar.py
sal/dataclass/core/string.py
sal/dataclass/signal/__init__.py
sal/dataclass/signal/signal.py
sal/dataclass/signal/subobject.py
sal/dataclass/signal/dimension/__init__.py
sal/dataclass/signal/dimension/array.py
sal/dataclass/signal/dimension/base.py
sal/dataclass/signal/dimension/calculated.py
sal/dataclass/signal/error/__init__.py
sal/dataclass/signal/error/asymmetric.py
sal/dataclass/signal/error/base.py
sal/dataclass/signal/error/constant.py
sal/dataclass/signal/error/symmetric.py
sal/dataclass/signal/mask/__init__.py
sal/dataclass/signal/mask/array.py
sal/dataclass/signal/mask/base.py
sal/dataclass/signal/mask/scalar.py
sal/server/__init__.py
sal/server/auth.py
sal/server/main.py
sal/server/interface/__init__.py
sal/server/interface/authentication.py
sal/server/interface/authorisation.py
sal/server/interface/persistence.py
sal/server/providers/__init__.py
sal/server/providers/ldap.py
sal/server/resource/__init__.py
sal/server/resource/authenticator.py
sal/server/resource/data.py
sal/server/resource/permission.py
sal/server/resource/root.py
sal/tests/__init__.py
sal/tests/server/__init__.py
sal/tests/server/conftest.py
sal/tests/server/constants.py
sal/tests/server/functional/__init__.py
sal/tests/server/functional/test_exceptions.py
sal/tests/server/functional/test_resources.py
sal/tests/server/unit/__init__.py
sal/tests/server/unit/test_auth.py
sal/tests/server/unit/test_authenticator.py
sal/tests/server/unit/test_data.py
sal/tests/server/unit/test_ldap.py
sal-1.2.5.dist-info/LICENCE.txt
sal-1.2.5.dist-info/METADATA
sal-1.2.5.dist-info/WHEEL
sal-1.2.5.dist-info/top_level.txt
sal-1.2.5.dist-info/RECORD
